alpha.py
roman.py
sequ
setup.py
SeqU.egg-info/PKG-INFO
SeqU.egg-info/SOURCES.txt
SeqU.egg-info/dependency_links.txt
SeqU.egg-info/top_level.txt