Metadata-Version: 1.1
Name: SeqU
Version: 1.1.1
Summary: Extended implemenation of the Unix seq command
Home-page: https://github.com/cameronbwhite/SeqU
Author: Cameron Brandon White
Author-email: cameronbwhite90@gmail.com
License: BSD
Platform: UNKNOWN
Classifier: Development Status :: 5 - Production/Stable
Classifier: License :: OSI Approved :: BSD License
Classifier: Intended Audience :: End Users/Desktop
Classifier: Operating System :: OS Independent
Classifier: Programming Language :: Python :: 3.3
Classifier: Topic :: Utilities
